NiukeDianqigongchengshiQiuzhiJingyanFenxiang20212022Fix1/README.md
NiukeDianqigongchengshiQiuzhiJingyanFenxiang20212022Fix1/__init__.py
NiukeDianqigongchengshiQiuzhiJingyanFenxiang20212022Fix1/__main__.py
NiukeDianqigongchengshiQiuzhiJingyanFenxiang20212022Fix1/file.epub
NiukeDianqigongchengshiQiuzhiJingyanFenxiang20212022Fix1/index.html
NiukeDianqigongchengshiQiuzhiJingyanFenxiang20212022Fix1/css/__init__.py
NiukeDianqigongchengshiQiuzhiJingyanFenxiang20212022Fix1/css/annotations.css
NiukeDianqigongchengshiQiuzhiJingyanFenxiang20212022Fix1/css/main.css
NiukeDianqigongchengshiQiuzhiJingyanFenxiang20212022Fix1/css/normalize.css
NiukeDianqigongchengshiQiuzhiJingyanFenxiang20212022Fix1/css/popup.css
NiukeDianqigongchengshiQiuzhiJingyanFenxiang20212022Fix1/font/__init__.py
NiukeDianqigongchengshiQiuzhiJingyanFenxiang20212022Fix1/font/fontello.eot
NiukeDianqigongchengshiQiuzhiJingyanFenxiang20212022Fix1/font/fontello.svg
NiukeDianqigongchengshiQiuzhiJingyanFenxiang20212022Fix1/font/fontello.ttf
NiukeDianqigongchengshiQiuzhiJingyanFenxiang20212022Fix1/font/fontello.woff
NiukeDianqigongchengshiQiuzhiJingyanFenxiang20212022Fix1/img/__init__.py
NiukeDianqigongchengshiQiuzhiJingyanFenxiang20212022Fix1/img/annotator-glyph-sprite.png
NiukeDianqigongchengshiQiuzhiJingyanFenxiang20212022Fix1/img/annotator-icon-sprite.png
NiukeDianqigongchengshiQiuzhiJingyanFenxiang20212022Fix1/img/apple-touch-icon.png
NiukeDianqigongchengshiQiuzhiJingyanFenxiang20212022Fix1/img/cancelfullscreen.png
NiukeDianqigongchengshiQiuzhiJingyanFenxiang20212022Fix1/img/close.png
NiukeDianqigongchengshiQiuzhiJingyanFenxiang20212022Fix1/img/fullscreen.png
NiukeDianqigongchengshiQiuzhiJingyanFenxiang20212022Fix1/img/loader.gif
NiukeDianqigongchengshiQiuzhiJingyanFenxiang20212022Fix1/img/menu-icon.png
NiukeDianqigongchengshiQiuzhiJingyanFenxiang20212022Fix1/img/save.png
NiukeDianqigongchengshiQiuzhiJingyanFenxiang20212022Fix1/img/saved.png
niuke_dianqigongchengshi_qiuzhi_jingyan_fenxiang_2021_2022_fix1-2025.3.25.0.dist-info/METADATA
niuke_dianqigongchengshi_qiuzhi_jingyan_fenxiang_2021_2022_fix1-2025.3.25.0.dist-info/WHEEL
niuke_dianqigongchengshi_qiuzhi_jingyan_fenxiang_2021_2022_fix1-2025.3.25.0.dist-info/entry_points.txt
niuke_dianqigongchengshi_qiuzhi_jingyan_fenxiang_2021_2022_fix1-2025.3.25.0.dist-info/top_level.txt
niuke_dianqigongchengshi_qiuzhi_jingyan_fenxiang_2021_2022_fix1-2025.3.25.0.dist-info/RECORD
